peppermining/__init__.py
peppermining/main.py
peppermining/pepper.py
peppermining/peppermining.py
peppermining/conformance/__init__.py
peppermining/conformance/conformance.py
peppermining/conformance/process_model.py
peppermining/conformance/root_cause_analysis.py
peppermining/conformance/violation/__init__.py
peppermining/conformance/violation/pepper_violation.py
peppermining/conformance/violation/run_by_same_user.py
peppermining/conformance/violation/undesired_activity.py
peppermining/conformance/violation/undesired_connection.py
peppermining/conformance/violation/undesired_end.py
peppermining/conformance/violation/undesired_start.py
peppermining/filters/__init__.py
peppermining/filters/case_activity_filter.py
peppermining/filters/case_between_time_filter.py
peppermining/filters/case_end_activity_filter.py
peppermining/filters/case_filter.py
peppermining/filters/case_size_filter.py
peppermining/filters/case_start_activity_filter.py
peppermining/filters/pepper_filter.py
peppermining/filters/variant_filter.py
peppermining/kpi/__init__.py
peppermining/kpi/average_events_per_case.py
peppermining/kpi/number_of_activities.py
peppermining/kpi/number_of_cases.py
peppermining/kpi/number_of_events.py
peppermining/kpi/pepper_kpi.py
peppermining/kpi/rework.py
peppermining/kpi/throughput_time.py
peppermining/utils/__init__.py
peppermining/utils/enum.py
src/__init__.py
src/peppermining.py
peppermining-0.1.1.dist-info/LICENSE.txt
peppermining-0.1.1.dist-info/METADATA
peppermining-0.1.1.dist-info/WHEEL
peppermining-0.1.1.dist-info/top_level.txt
peppermining-0.1.1.dist-info/RECORD
