Metadata-Version: 2.1
Name: peppermining
Version: 0.1.1
Summary: PepperMining is a free Process Mining framework.
Home-page: https://github.com/ThoberDetofeno/peppermining
Author: Thober Detofeno
Author-email: Thober Detofeno <thober@gmail.com>
License: MIT
Project-URL: Homepage, https://github.com/ThoberDetofeno/peppermining
Project-URL: Bug Tracker, https://github.com/ThoberDetofeno/peppermining/issues
Keywords: python,process mining
Classifier: Development Status :: 1 - Planning
Classifier: Programming Language :: Python :: 3
Classifier: License :: OSI Approved :: MIT License
Classifier: Operating System :: OS Independent
Requires-Python: >=3.8
License-File: LICENSE.txt
Requires-Dist: numpy
Requires-Dist: pandas
Requires-Dist: pydot
Requires-Dist: deepdiff
